{"ts":"2026-04-18T09:55:36+00:00","universe":634,"cohort":40,"cohort_min_v1m":50000.0,"weights":{"cascade":1.5,"vol_rise":1.0,"oi_rise":1.0,"flow":1.0,"crowding":-0.8,"pumpiness":-0.8},"leaderboard":[{"s":"ALICEUSDT","sms":13.34,"zc":1.34,"zv":4.96,"zo":5.37,"zf":0.56,"zx":-0.31,"zp":-0.25,"c5m":-2.67,"c15m":-0.21,"c1h":7.68,"c4h":39.84,"c12h":55.47,"c1d":59.05,"price":0.1935,"mcap":0,"fund":-0.8872,"rng":0.56,"v1m":225678,"t5m":10948},{"s":"HIGHUSDT","sms":10.93,"zc":6.0,"zv":-0.14,"zo":0.42,"zf":1.2,"zx":-0.31,"zp":-0.25,"c5m":-0.71,"c15m":5.83,"c1h":34.81,"c4h":60.01,"c12h":315.01,"c1d":323.58,"price":0.4995,"mcap":0,"fund":-0.7872,"rng":0.82,"v1m":1779714,"t5m":54883},{"s":"NOMUSDT","sms":3.61,"zc":0.44,"zv":0.71,"zo":1.54,"zf":0.5,"zx":-0.31,"zp":0.07,"c5m":5.48,"c15m":5.0,"c1h":5.6,"c4h":14.71,"c12h":23.46,"c1d":23.63,"price":0.003605,"mcap":0,"fund":-0.2056,"rng":0.91,"v1m":95952,"t5m":15087},{"s":"SIRENUSDT","sms":3.24,"zc":-0.24,"zv":2.17,"zo":0.81,"zf":0.17,"zx":-0.31,"zp":-0.25,"c5m":-0.12,"c15m":5.37,"c1h":-11.66,"c4h":5.51,"c12h":2.68,"c1d":-6.29,"price":0.7427,"mcap":1739670197,"fund":-0.094,"rng":0.51,"v1m":293285,"t5m":17722},{"s":"PORTALUSDT","sms":2.07,"zc":-0.07,"zv":1.54,"zo":-0.14,"zf":0.32,"zx":-0.31,"zp":-0.25,"c5m":-2.25,"c15m":-1.14,"c1h":4.83,"c4h":-7.4,"c12h":45.14,"c1d":49.52,"price":0.01399,"mcap":0,"fund":-0.1467,"rng":0.44,"v1m":84307,"t5m":5414},{"s":"DEXEUSDT","sms":1.91,"zc":0.22,"zv":-0.16,"zo":-0.03,"zf":1.33,"zx":-0.31,"zp":-0.25,"c5m":-0.64,"c15m":-0.53,"c1h":4.05,"c4h":7.44,"c12h":17.4,"c1d":21.64,"price":14.485,"mcap":347889992,"fund":0.005,"rng":0.95,"v1m":72839,"t5m":5721},{"s":"UBUSDT","sms":1.64,"zc":-0.24,"zv":1.82,"zo":-0.16,"zf":0.74,"zx":0.74,"zp":-0.25,"c5m":0.32,"c15m":-0.98,"c1h":-5.18,"c4h":0.45,"c12h":0.57,"c1d":6.14,"price":0.04079,"mcap":85288459,"fund":0.033,"rng":0.68,"v1m":57838,"t5m":754},{"s":"NEARUSDT","sms":1.21,"zc":-0.22,"zv":-0.43,"zo":0.03,"zf":2.11,"zx":-0.31,"zp":0.53,"c5m":-0.35,"c15m":-0.14,"c1h":0.21,"c4h":0.57,"c12h":-0.78,"c1d":-1.05,"price":1.408,"mcap":1682000735,"fund":-0.0075,"rng":0.54,"v1m":52632,"t5m":506},{"s":"HYPEUSDT","sms":0.49,"zc":-0.22,"zv":-0.29,"zo":-0.04,"zf":0.71,"zx":-0.31,"zp":-0.25,"c5m":-0.06,"c15m":-0.0,"c1h":-0.44,"c4h":-0.24,"c12h":0.37,"c1d":1.26,"price":44.709,"mcap":9079647835,"fund":-0.0004,"rng":0.63,"v1m":59036,"t5m":1268},{"s":"RAVEUSDT","sms":0.4,"zc":-0.33,"zv":-0.27,"zo":0.32,"zf":0.39,"zx":-0.31,"zp":-0.25,"c5m":0.11,"c15m":-4.55,"c1h":-13.87,"c4h":-17.42,"c12h":2.95,"c1d":20.36,"price":21.90856,"mcap":64265085,"fund":-0.1236,"rng":0.49,"v1m":2801086,"t5m":67306},{"s":"THETAUSDT","sms":0.38,"zc":-0.19,"zv":-0.34,"zo":0.15,"zf":0.4,"zx":-0.31,"zp":-0.25,"c5m":-0.78,"c15m":1.0,"c1h":2.29,"c4h":-6.4,"c12h":12.92,"c1d":19.57,"price":0.2404,"mcap":161224902,"fund":-0.2003,"rng":0.54,"v1m":84141,"t5m":4583},{"s":"XRPUSDT","sms":0.02,"zc":-0.24,"zv":-0.33,"zo":-0.11,"zf":0.54,"zx":-0.31,"zp":-0.03,"c5m":-0.23,"c15m":-0.14,"c1h":-0.28,"c4h":-1.34,"c12h":-2.14,"c1d":-0.19,"price":1.4473,"mcap":88443180107,"fund":0.0042,"rng":0.2,"v1m":640017,"t5m":6228},{"s":"ORDIUSDT","sms":-0.0,"zc":-0.27,"zv":-0.53,"zo":0.09,"zf":0.43,"zx":-0.31,"zp":-0.23,"c5m":0.05,"c15m":-0.02,"c1h":0.07,"c4h":-4.13,"c12h":-9.91,"c1d":-22.83,"price":5.631,"mcap":50402542,"fund":0.005,"rng":0.08,"v1m":118136,"t5m":4969},{"s":"XRPUSDC","sms":-0.09,"zc":-0.24,"zv":-0.33,"zo":-0.14,"zf":0.4,"zx":-0.31,"zp":-0.11,"c5m":-0.21,"c15m":-0.13,"c1h":-0.29,"c4h":-1.34,"c12h":-2.11,"c1d":-0.17,"price":1.4478,"mcap":88443180107,"fund":0.01,"rng":0.2,"v1m":152592,"t5m":1434},{"s":"ZECUSDT","sms":-0.26,"zc":-0.23,"zv":-0.46,"zo":-0.12,"zf":0.21,"zx":-0.31,"zp":-0.25,"c5m":0.08,"c15m":0.05,"c1h":-0.73,"c4h":-1.78,"c12h":1.28,"c1d":-1.15,"price":331.36,"mcap":3838638168,"fund":-0.0036,"rng":0.27,"v1m":111900,"t5m":2012},{"s":"DOTUSDT","sms":-0.39,"zc":-0.24,"zv":-0.31,"zo":-0.28,"zf":0.15,"zx":-0.31,"zp":-0.2,"c5m":-0.31,"c15m":-0.61,"c1h":-0.53,"c4h":-1.36,"c12h":-1.88,"c1d":-0.76,"price":1.305,"mcap":2402783291,"fund":0.005,"rng":0.19,"v1m":60744,"t5m":542},{"s":"1000PEPEUSDT","sms":-0.44,"zc":-0.24,"zv":-0.41,"zo":-0.13,"zf":0.01,"zx":-0.31,"zp":-0.25,"c5m":-0.02,"c15m":-0.11,"c1h":0.02,"c4h":-1.67,"c12h":-2.87,"c1d":-1.02,"price":0.0038917,"mcap":1470547047,"fund":-0.0089,"rng":0.13,"v1m":153041,"t5m":3638},{"s":"ETHUSDT","sms":-0.45,"zc":-0.24,"zv":-0.33,"zo":-0.42,"zf":0.21,"zx":-0.31,"zp":-0.25,"c5m":-0.1,"c15m":-0.11,"c1h":-0.21,"c4h":-1.4,"c12h":-2.28,"c1d":0.62,"price":2371.68,"mcap":259404297691,"fund":-0.0052,"rng":0.29,"v1m":2887477,"t5m":6230},{"s":"PENGUUSDT","sms":-0.54,"zc":-0.24,"zv":-0.23,"zo":-0.01,"zf":-0.37,"zx":-0.31,"zp":-0.25,"c5m":-0.17,"c15m":-0.34,"c1h":-0.6,"c4h":-2.06,"c12h":-2.88,"c1d":-1.42,"price":0.007595,"mcap":445237978,"fund":0.0028,"rng":0.12,"v1m":74344,"t5m":627},{"s":"\u5e01\u5b89\u4eba\u751fUSDT","sms":-0.57,"zc":-0.18,"zv":-0.48,"zo":-0.77,"zf":0.51,"zx":-0.31,"zp":-0.25,"c5m":1.28,"c15m":1.1,"c1h":-5.52,"c4h":-6.6,"c12h":24.21,"c1d":39.42,"price":0.49743,"mcap":49564158,"fund":0.005,"rng":0.58,"v1m":1002316,"t5m":17729},{"s":"ADAUSDT","sms":-0.6,"zc":-0.24,"zv":-0.37,"zo":-0.26,"zf":-0.05,"zx":-0.31,"zp":-0.25,"c5m":-0.2,"c15m":-0.27,"c1h":-0.51,"c4h":-1.32,"c12h":-2.46,"c1d":-1.74,"price":0.2541,"mcap":9637727086,"fund":0.0048,"rng":0.05,"v1m":71809,"t5m":962},{"s":"MOVRUSDT","sms":-0.62,"zc":-0.33,"zv":-0.6,"zo":-0.91,"zf":0.95,"zx":-0.31,"zp":-0.25,"c5m":-0.57,"c15m":-3.23,"c1h":-1.68,"c4h":-6.29,"c12h":-21.71,"c1d":-33.17,"price":2.279,"mcap":0,"fund":0.005,"rng":0.02,"v1m":150471,"t5m":4476},{"s":"SOLUSDT","sms":-0.88,"zc":-0.23,"zv":-0.35,"zo":-0.21,"zf":0.23,"zx":-0.31,"zp":0.57,"c5m":-0.17,"c15m":-0.08,"c1h":0.09,"c4h":-0.97,"c12h":-1.9,"c1d":-1.25,"price":87.44,"mcap":52139945431,"fund":-0.0078,"rng":0.11,"v1m":771822,"t5m":3570},{"s":"AVAXUSDT","sms":-0.97,"zc":-0.24,"zv":-0.34,"zo":-0.21,"zf":-0.4,"zx":-0.31,"zp":-0.1,"c5m":-0.24,"c15m":-0.24,"c1h":-0.33,"c4h":-1.65,"c12h":-2.84,"c1d":-1.35,"price":9.516,"mcap":4099791829,"fund":-0.0019,"rng":0.08,"v1m":58016,"t5m":1268},{"s":"LIGHTUSDT","sms":-1.05,"zc":-0.02,"zv":0.16,"zo":0.43,"zf":1.45,"zx":4.07,"zp":-0.25,"c5m":0.48,"c15m":-0.71,"c1h":6.35,"c4h":5.99,"c12h":4.36,"c1d":22.91,"price":0.253,"mcap":14503294,"fund":0.0897,"rng":0.8,"v1m":53524,"t5m":3417},{"s":"ASTERUSDT","sms":-1.05,"zc":-0.24,"zv":0.14,"zo":-0.48,"zf":-0.79,"zx":-0.31,"zp":-0.25,"c5m":-0.01,"c15m":-0.07,"c1h":-1.47,"c4h":-2.07,"c12h":-2.29,"c1d":-2.03,"price":0.6704,"mcap":1626405629,"fund":0.005,"rng":0.14,"v1m":73743,"t5m":589},{"s":"SOLUSDC","sms":-1.1,"zc":-0.23,"zv":-0.36,"zo":-0.31,"zf":-0.16,"zx":-0.31,"zp":0.22,"c5m":-0.14,"c15m":-0.07,"c1h":0.11,"c4h":-0.95,"c12h":-1.87,"c1d":-1.25,"price":87.48,"mcap":52139945431,"fund":0.0005,"rng":0.12,"v1m":60442,"t5m":752},{"s":"ENAUSDT","sms":-1.13,"zc":-0.26,"zv":-0.29,"zo":-0.23,"zf":-0.68,"zx":-0.31,"zp":-0.25,"c5m":0.04,"c15m":-0.08,"c1h":-0.9,"c4h":-1.68,"c12h":-6.27,"c1d":8.32,"price":0.1226,"mcap":787132671,"fund":0.005,"rng":0.48,"v1m":81168,"t5m":2055},{"s":"EDGEUSDT","sms":-1.19,"zc":-0.04,"zv":-0.04,"zo":0.05,"zf":1.08,"zx":3.03,"zp":-0.25,"c5m":0.11,"c15m":-0.07,"c1h":2.11,"c4h":2.88,"c12h":7.31,"c1d":5.09,"price":1.4146,"mcap":26269469,"fund":0.072,"rng":0.91,"v1m":117915,"t5m":8189},{"s":"ETHUSDC","sms":-1.25,"zc":-0.24,"zv":-0.4,"zo":-0.08,"zf":-0.86,"zx":-0.31,"zp":-0.25,"c5m":-0.1,"c15m":-0.11,"c1h":-0.22,"c4h":-1.4,"c12h":-2.26,"c1d":0.64,"price":2373.01,"mcap":259404297691,"fund":0.0042,"rng":0.29,"v1m":447004,"t5m":1274},{"s":"DOGEUSDT","sms":-1.35,"zc":-0.24,"zv":-0.31,"zo":-0.18,"zf":-0.79,"zx":-0.31,"zp":-0.06,"c5m":-0.15,"c15m":-0.06,"c1h":0.2,"c4h":-1.84,"c12h":-3.15,"c1d":-1.88,"price":0.09695,"mcap":14577729815,"fund":-0.0001,"rng":0.07,"v1m":379438,"t5m":3454},{"s":"SUIUSDT","sms":-1.4,"zc":-0.24,"zv":-0.28,"zo":-0.2,"zf":-1.01,"zx":-0.31,"zp":-0.25,"c5m":-0.16,"c15m":-0.23,"c1h":-0.37,"c4h":-1.73,"c12h":-2.67,"c1d":-1.26,"price":0.984,"mcap":3738481302,"fund":-0.0035,"rng":0.05,"v1m":59913,"t5m":905},{"s":"GIGGLEUSDT","sms":-1.49,"zc":-0.25,"zv":-0.58,"zo":-0.81,"zf":-0.17,"zx":-0.31,"zp":-0.25,"c5m":0.36,"c15m":-1.76,"c1h":-2.83,"c4h":-9.41,"c12h":4.09,"c1d":3.73,"price":42.06,"mcap":26588911,"fund":0.005,"rng":0.34,"v1m":119048,"t5m":3112},{"s":"BNBUSDT","sms":-1.5,"zc":-0.23,"zv":-0.51,"zo":-0.27,"zf":-0.82,"zx":-0.31,"zp":-0.25,"c5m":-0.09,"c15m":-0.07,"c1h":-0.23,"c4h":-1.57,"c12h":-1.1,"c1d":0.47,"price":635.59,"mcap":86780721628,"fund":0.0,"rng":0.32,"v1m":90025,"t5m":1473},{"s":"BTCUSDT","sms":-1.79,"zc":-0.23,"zv":-0.26,"zo":-0.29,"zf":-1.32,"zx":-0.31,"zp":-0.23,"c5m":-0.12,"c15m":-0.04,"c1h":-0.23,"c4h":-0.7,"c12h":-1.14,"c1d":0.93,"price":76491.8,"mcap":1420122125224,"fund":-0.0055,"rng":0.45,"v1m":4382175,"t5m":5198},{"s":"BTCUSDC","sms":-1.93,"zc":-0.23,"zv":-0.39,"zo":-0.17,"zf":-1.43,"zx":-0.31,"zp":-0.19,"c5m":-0.12,"c15m":-0.03,"c1h":-0.2,"c4h":-0.7,"c12h":-1.13,"c1d":0.97,"price":76531.2,"mcap":1420122125224,"fund":-0.002,"rng":0.44,"v1m":671853,"t5m":1100},{"s":"XAUUSDT","sms":-2.63,"zc":-0.22,"zv":-0.32,"zo":-0.08,"zf":-2.34,"zx":-0.31,"zp":-0.25,"c5m":-0.02,"c15m":0.0,"c1h":-0.0,"c4h":-0.13,"c12h":-0.22,"c1d":0.65,"price":4824.54,"mcap":0,"fund":-0.0072,"rng":0.38,"v1m":96829,"t5m":189},{"s":"\u6211\u8e0f\u9a6c\u6765\u4e86USDT","sms":-2.64,"zc":-0.27,"zv":-0.44,"zo":-2.1,"zf":-0.14,"zx":-0.31,"zp":-0.25,"c5m":0.61,"c15m":-6.43,"c1h":-13.96,"c4h":-23.47,"c12h":25.41,"c1d":39.53,"price":0.01339,"mcap":0,"fund":0.005,"rng":0.31,"v1m":194154,"t5m":6272},{"s":"CRCLUSDT","sms":-3.86,"zc":-0.23,"zv":-0.27,"zo":0.0,"zf":-3.35,"zx":-0.31,"zp":0.18,"c5m":-0.11,"c15m":0.1,"c1h":0.04,"c4h":-0.08,"c12h":-0.64,"c1d":-2.89,"price":104.63,"mcap":0,"fund":0.0,"rng":0.2,"v1m":50097,"t5m":143},{"s":"MUSDT","sms":-8.04,"zc":-0.16,"zv":-0.33,"zo":-0.08,"zf":0.08,"zx":3.21,"zp":6.12,"c5m":1.0,"c15m":-2.02,"c1h":0.1,"c4h":-1.71,"c12h":18.0,"c1d":20.72,"price":4.4858,"mcap":3061642420,"fund":0.0751,"rng":0.73,"v1m":59066,"t5m":6107}]}