{"ts":"2026-04-18T15:30:37+00:00","universe":634,"cohort":38,"cohort_min_v1m":50000.0,"weights":{"cascade":1.5,"vol_rise":1.0,"oi_rise":1.0,"flow":1.0,"crowding":-0.8,"pumpiness":-0.8},"leaderboard":[{"s":"PROMUSDT","sms":17.85,"zc":5.26,"zv":5.17,"zo":4.73,"zf":-0.22,"zx":-0.16,"zp":-0.18,"c5m":3.05,"c15m":6.94,"c1h":24.55,"c4h":55.31,"c12h":57.19,"c1d":61.28,"price":2.629,"mcap":19865644,"fund":-0.2606,"rng":0.98,"v1m":410839,"t5m":26368},{"s":"TRXUSDT","sms":3.85,"zc":-0.15,"zv":-0.14,"zo":-0.04,"zf":3.97,"zx":-0.16,"zp":-0.18,"c5m":0.0,"c15m":0.06,"c1h":0.42,"c4h":0.63,"c12h":0.95,"c1d":1.68,"price":0.32982,"mcap":28895221976,"fund":0.007,"rng":0.97,"v1m":50332,"t5m":414},{"s":"API3USDT","sms":3.36,"zc":2.16,"zv":1.64,"zo":3.27,"zf":-0.06,"zx":-0.16,"zp":6.08,"c5m":1.21,"c15m":1.61,"c1h":0.1,"c4h":25.57,"c12h":33.97,"c1d":34.05,"price":0.416,"mcap":39825813,"fund":-1.0655,"rng":0.77,"v1m":153478,"t5m":10562},{"s":"RONINUSDT","sms":2.8,"zc":0.12,"zv":1.46,"zo":0.75,"zf":0.13,"zx":-0.16,"zp":-0.18,"c5m":0.39,"c15m":-2.59,"c1h":4.63,"c4h":2.11,"c12h":4.2,"c1d":4.41,"price":0.1016,"mcap":0,"fund":0.005,"rng":0.48,"v1m":85307,"t5m":1690},{"s":"UBUSDT","sms":1.35,"zc":0.04,"zv":1.5,"zo":-0.17,"zf":-0.27,"zx":-0.16,"zp":-0.11,"c5m":0.6,"c15m":0.7,"c1h":0.95,"c4h":1.48,"c12h":4.24,"c1d":5.54,"price":0.04078,"mcap":85288459,"fund":0.0137,"rng":0.63,"v1m":53315,"t5m":466},{"s":"ENAUSDT","sms":1.13,"zc":-0.04,"zv":-0.34,"zo":-0.19,"zf":1.45,"zx":-0.16,"zp":-0.18,"c5m":0.33,"c15m":1.12,"c1h":2.2,"c4h":2.93,"c12h":0.54,"c1d":6.52,"price":0.12357,"mcap":787132671,"fund":0.0039,"rng":0.37,"v1m":156898,"t5m":3152},{"s":"BTCUSDT","sms":0.97,"zc":-0.24,"zv":-0.4,"zo":-0.26,"zf":1.7,"zx":-0.16,"zp":-0.18,"c5m":-0.0,"c15m":-0.01,"c1h":0.04,"c4h":0.16,"c12h":-1.26,"c1d":-1.92,"price":76164.8,"mcap":1420122125224,"fund":-0.0046,"rng":0.18,"v1m":2482038,"t5m":3694},{"s":"MEUSDT","sms":0.87,"zc":0.23,"zv":-0.16,"zo":0.13,"zf":0.29,"zx":-0.16,"zp":-0.18,"c5m":0.6,"c15m":1.92,"c1h":3.0,"c4h":5.8,"c12h":5.32,"c1d":5.04,"price":0.1168,"mcap":52853205,"fund":-0.0183,"rng":0.98,"v1m":58547,"t5m":1310},{"s":"MUSDT","sms":0.66,"zc":-0.46,"zv":0.65,"zo":-0.08,"zf":0.5,"zx":-0.16,"zp":-0.17,"c5m":3.18,"c15m":5.06,"c1h":6.25,"c4h":-16.64,"c12h":-13.6,"c1d":-0.07,"price":3.8189,"mcap":3061642420,"fund":0.0136,"rng":0.39,"v1m":134744,"t5m":27324},{"s":"SOLUSDT","sms":0.08,"zc":-0.25,"zv":-0.4,"zo":-0.14,"zf":0.71,"zx":-0.16,"zp":-0.18,"c5m":0.02,"c15m":0.05,"c1h":0.03,"c4h":0.01,"c12h":-2.16,"c1d":-3.23,"price":86.76,"mcap":52139945431,"fund":-0.0082,"rng":0.12,"v1m":356847,"t5m":1823},{"s":"ZECUSDT","sms":-0.05,"zc":-0.25,"zv":-0.41,"zo":-0.11,"zf":0.59,"zx":-0.16,"zp":-0.16,"c5m":0.18,"c15m":0.28,"c1h":0.32,"c4h":0.49,"c12h":-3.56,"c1d":-5.18,"price":324.6,"mcap":3838638168,"fund":0.0059,"rng":0.16,"v1m":70107,"t5m":1950},{"s":"HYPEUSDT","sms":-0.17,"zc":-0.24,"zv":-0.39,"zo":-0.2,"zf":0.5,"zx":-0.16,"zp":-0.18,"c5m":-0.01,"c15m":0.2,"c1h":0.37,"c4h":0.43,"c12h":-2.25,"c1d":-0.83,"price":44.384,"mcap":9079647835,"fund":0.0021,"rng":0.27,"v1m":94190,"t5m":1610},{"s":"ETHUSDC","sms":-0.19,"zc":-0.24,"zv":-0.36,"zo":-0.18,"zf":0.44,"zx":-0.16,"zp":-0.18,"c5m":0.03,"c15m":0.09,"c1h":0.31,"c4h":0.32,"c12h":-2.18,"c1d":-3.21,"price":2364.11,"mcap":259404297691,"fund":-0.0061,"rng":0.17,"v1m":466198,"t5m":716},{"s":"AVAXUSDT","sms":-0.21,"zc":-0.25,"zv":-0.37,"zo":-0.19,"zf":0.45,"zx":-0.16,"zp":-0.18,"c5m":-0.03,"c15m":-0.11,"c1h":0.07,"c4h":0.16,"c12h":-2.71,"c1d":-3.9,"price":9.42,"mcap":4099791829,"fund":-0.0165,"rng":0.15,"v1m":65678,"t5m":543},{"s":"BTCUSDC","sms":-0.23,"zc":-0.24,"zv":-0.36,"zo":-0.27,"zf":0.48,"zx":-0.16,"zp":-0.18,"c5m":0.01,"c15m":-0.01,"c1h":0.05,"c4h":0.15,"c12h":-1.27,"c1d":-1.94,"price":76197.5,"mcap":1420122125224,"fund":-0.0027,"rng":0.17,"v1m":579296,"t5m":449},{"s":"DOTUSDT","sms":-0.23,"zc":-0.23,"zv":-0.38,"zo":-0.17,"zf":0.39,"zx":-0.16,"zp":-0.18,"c5m":0.08,"c15m":0.62,"c1h":0.7,"c4h":0.54,"c12h":-1.96,"c1d":-2.41,"price":1.298,"mcap":2402783291,"fund":0.0095,"rng":0.26,"v1m":52038,"t5m":348},{"s":"XRPUSDT","sms":-0.26,"zc":-0.24,"zv":-0.35,"zo":-0.15,"zf":0.36,"zx":-0.16,"zp":-0.15,"c5m":0.06,"c15m":0.29,"c1h":0.11,"c4h":0.31,"c12h":-2.18,"c1d":-3.51,"price":1.4385,"mcap":88443180107,"fund":0.0016,"rng":0.2,"v1m":228344,"t5m":1650},{"s":"TAOUSDT","sms":-0.29,"zc":-0.24,"zv":-0.37,"zo":-0.16,"zf":0.32,"zx":-0.16,"zp":-0.18,"c5m":0.05,"c15m":0.08,"c1h":-0.08,"c4h":-0.07,"c12h":-1.52,"c1d":-3.34,"price":249.44,"mcap":2744859366,"fund":-0.0118,"rng":0.18,"v1m":61734,"t5m":1064},{"s":"1000PEPEUSDT","sms":-0.36,"zc":-0.24,"zv":-0.35,"zo":-0.18,"zf":0.27,"zx":-0.16,"zp":-0.18,"c5m":0.02,"c15m":0.23,"c1h":0.48,"c4h":-0.16,"c12h":-1.94,"c1d":-4.77,"price":0.0038405,"mcap":1470547047,"fund":0.0061,"rng":0.15,"v1m":186010,"t5m":3187},{"s":"HIGHUSDT","sms":-0.51,"zc":0.07,"zv":-0.41,"zo":-0.69,"zf":0.2,"zx":-0.16,"zp":-0.18,"c5m":-0.96,"c15m":-4.58,"c1h":-13.46,"c4h":-7.53,"c12h":52.2,"c1d":238.46,"price":0.3896,"mcap":0,"fund":-0.7269,"rng":0.58,"v1m":771122,"t5m":23054},{"s":"ETHUSDT","sms":-0.55,"zc":-0.24,"zv":-0.37,"zo":-0.21,"zf":0.12,"zx":-0.16,"zp":-0.18,"c5m":0.02,"c15m":0.08,"c1h":0.32,"c4h":0.34,"c12h":-2.18,"c1d":-3.21,"price":2363.08,"mcap":259404297691,"fund":-0.0145,"rng":0.18,"v1m":1786695,"t5m":4113},{"s":"ALICEUSDT","sms":-0.58,"zc":-0.03,"zv":-0.38,"zo":-0.06,"zf":-0.37,"zx":-0.16,"zp":-0.18,"c5m":-0.62,"c15m":-2.73,"c1h":-4.56,"c4h":-16.67,"c12h":41.65,"c1d":54.37,"price":0.1903,"mcap":0,"fund":-0.2729,"rng":0.48,"v1m":155563,"t5m":5489},{"s":"ORDIUSDT","sms":-0.59,"zc":-0.28,"zv":-0.32,"zo":0.03,"zf":-0.16,"zx":-0.16,"zp":-0.18,"c5m":-0.11,"c15m":0.68,"c1h":1.34,"c4h":1.43,"c12h":-8.4,"c1d":-11.32,"price":5.597,"mcap":50402542,"fund":0.005,"rng":0.14,"v1m":129723,"t5m":6807},{"s":"SUIUSDT","sms":-0.7,"zc":-0.25,"zv":-0.41,"zo":-0.18,"zf":-0.0,"zx":-0.16,"zp":-0.17,"c5m":-0.05,"c15m":-0.06,"c1h":0.05,"c4h":-0.19,"c12h":-2.93,"c1d":-5.8,"price":0.967,"mcap":3738481302,"fund":0.0074,"rng":0.13,"v1m":53672,"t5m":564},{"s":"ADAUSDT","sms":-1.06,"zc":-0.25,"zv":-0.33,"zo":-0.22,"zf":-0.4,"zx":-0.16,"zp":-0.18,"c5m":-0.04,"c15m":-0.04,"c1h":-0.12,"c4h":-0.32,"c12h":-2.41,"c1d":-4.85,"price":0.2511,"mcap":9637727086,"fund":-0.0064,"rng":0.1,"v1m":67940,"t5m":931},{"s":"BNBUSDT","sms":-1.06,"zc":-0.24,"zv":-0.38,"zo":-0.15,"zf":-0.4,"zx":-0.16,"zp":-0.12,"c5m":0.06,"c15m":0.07,"c1h":0.03,"c4h":-0.1,"c12h":-1.31,"c1d":-1.39,"price":633.86,"mcap":86780721628,"fund":0.0,"rng":0.14,"v1m":101203,"t5m":851},{"s":"DOGEUSDT","sms":-1.3,"zc":-0.25,"zv":-0.37,"zo":-0.22,"zf":-0.61,"zx":-0.16,"zp":-0.18,"c5m":0.02,"c15m":0.09,"c1h":0.25,"c4h":-0.02,"c12h":-2.63,"c1d":-4.55,"price":0.09613,"mcap":14577729815,"fund":-0.0072,"rng":0.11,"v1m":142268,"t5m":1508},{"s":"XMRUSDT","sms":-1.33,"zc":-0.25,"zv":-0.13,"zo":-0.08,"zf":-1.02,"zx":-0.16,"zp":-0.18,"c5m":-0.1,"c15m":0.15,"c1h":-0.28,"c4h":-1.28,"c12h":-0.72,"c1d":-2.54,"price":344.11,"mcap":6552652898,"fund":0.0111,"rng":0.08,"v1m":51919,"t5m":697},{"s":"RIVERUSDT","sms":-1.38,"zc":-0.44,"zv":-0.09,"zo":0.15,"zf":-0.96,"zx":-0.16,"zp":-0.05,"c5m":-0.07,"c15m":-0.12,"c1h":-0.04,"c4h":-9.91,"c12h":-12.21,"c1d":-10.25,"price":6.785,"mcap":502125724,"fund":0.0129,"rng":0.09,"v1m":73459,"t5m":3184},{"s":"\u5e01\u5b89\u4eba\u751fUSDT","sms":-1.49,"zc":-0.49,"zv":-0.06,"zo":-0.5,"zf":-0.46,"zx":-0.16,"zp":-0.18,"c5m":0.5,"c15m":0.95,"c1h":-8.89,"c4h":-12.74,"c12h":-6.26,"c1d":16.91,"price":0.43855,"mcap":49564158,"fund":0.005,"rng":0.33,"v1m":855579,"t5m":11338},{"s":"SIRENUSDT","sms":-1.55,"zc":-0.16,"zv":-0.41,"zo":-0.61,"zf":-0.4,"zx":-0.16,"zp":0.02,"c5m":-0.4,"c15m":-1.27,"c1h":0.45,"c4h":-5.99,"c12h":12.52,"c1d":7.5,"price":0.7487,"mcap":1739670197,"fund":-0.0201,"rng":0.5,"v1m":74531,"t5m":5621},{"s":"RAVEUSDT","sms":-1.84,"zc":-1.1,"zv":0.11,"zo":-0.74,"zf":0.17,"zx":-0.16,"zp":-0.18,"c5m":-3.66,"c15m":-5.3,"c1h":15.61,"c4h":-49.29,"c12h":-57.53,"c1d":-37.03,"price":10.55033,"mcap":64265085,"fund":-0.1497,"rng":0.09,"v1m":2976026,"t5m":101640},{"s":"FETUSDT","sms":-2.06,"zc":-0.25,"zv":-0.36,"zo":-0.09,"zf":-1.51,"zx":-0.16,"zp":-0.18,"c5m":0.0,"c15m":-0.27,"c1h":-0.62,"c4h":0.13,"c12h":-1.57,"c1d":-4.33,"price":0.2256,"mcap":493764462,"fund":-0.079,"rng":0.11,"v1m":54798,"t5m":428},{"s":"PORTALUSDT","sms":-2.4,"zc":-0.37,"zv":-0.44,"zo":-0.84,"zf":-0.84,"zx":-0.16,"zp":-0.18,"c5m":0.26,"c15m":-4.84,"c1h":-8.53,"c4h":-18.58,"c12h":12.07,"c1d":22.68,"price":0.0118,"mcap":0,"fund":-0.02,"rng":0.22,"v1m":74678,"t5m":3183},{"s":"ACEUSDT","sms":-2.52,"zc":-0.45,"zv":-0.35,"zo":-0.69,"zf":-1.08,"zx":-0.16,"zp":-0.18,"c5m":-0.52,"c15m":-4.53,"c1h":-6.77,"c4h":-14.67,"c12h":-1.68,"c1d":5.47,"price":0.1345,"mcap":0,"fund":-0.0191,"rng":0.13,"v1m":52574,"t5m":1608},{"s":"\u6211\u8e0f\u9a6c\u6765\u4e86USDT","sms":-2.92,"zc":-0.43,"zv":-0.3,"zo":-0.71,"zf":-1.53,"zx":-0.16,"zp":-0.18,"c5m":-0.97,"c15m":0.94,"c1h":-10.99,"c4h":-13.33,"c12h":2.59,"c1d":19.01,"price":0.012301,"mcap":0,"fund":0.0062,"rng":0.18,"v1m":94919,"t5m":5741},{"s":"GIGGLEUSDT","sms":-3.41,"zc":-0.45,"zv":-0.36,"zo":-0.52,"zf":-2.12,"zx":-0.16,"zp":-0.18,"c5m":-0.84,"c15m":-0.78,"c1h":-2.22,"c4h":-9.66,"c12h":-11.45,"c1d":-5.9,"price":37.81,"mcap":26588911,"fund":0.0042,"rng":0.01,"v1m":60594,"t5m":2802},{"s":"PLAYUSDT","sms":-3.66,"zc":1.34,"zv":-0.29,"zo":-0.07,"zf":-0.58,"zx":6.08,"zp":-0.18,"c5m":0.8,"c15m":1.25,"c1h":16.36,"c4h":11.95,"c12h":20.51,"c1d":15.01,"price":0.11179,"mcap":16086930,"fund":0.0251,"rng":0.96,"v1m":60323,"t5m":5880}]}